Boiler_Plate-0.0.1.dist-info/DESCRIPTION.rst
Boiler_Plate-0.0.1.dist-info/METADATA
Boiler_Plate-0.0.1.dist-info/RECORD
Boiler_Plate-0.0.1.dist-info/WHEEL
Boiler_Plate-0.0.1.dist-info/entry_points.txt
Boiler_Plate-0.0.1.dist-info/metadata.json
Boiler_Plate-0.0.1.dist-info/top_level.txt
boiler_plate/__init__.py
boiler_plate/_version.py
boiler_plate/cli.py
